fashionstar_uart_sdk/__init__.py
fashionstar_uart_sdk/uart_pocket_handler.py
fashionstar_uart_sdk/uservo.py
fashionstar_uart_sdk-1.3.8.dist-info/licenses/LICENSE.txt
fashionstar_uart_sdk-1.3.8.dist-info/METADATA
fashionstar_uart_sdk-1.3.8.dist-info/WHEEL
fashionstar_uart_sdk-1.3.8.dist-info/top_level.txt
fashionstar_uart_sdk-1.3.8.dist-info/RECORD
